aws_etl/__init__.py
aws_etl/redshift.py
aws_etl/utils.py
aws_etl_utils-0.0.3.dist-info/METADATA
aws_etl_utils-0.0.3.dist-info/RECORD
aws_etl_utils-0.0.3.dist-info/WHEEL
aws_etl_utils-0.0.3.dist-info/top_level.txt
