Metadata-Version: 2.1
Name: aws-etl-utils
Version: 0.0.3
Summary: AWS ETL Utility
Home-page: https://github.com/mferi/aws-etl-utils
Author: Maria Feria
Author-email: mferiaa@gmail.com
License: Apache 2.0
Platform: UNKNOWN
Classifier: Programming Language :: Python :: 3
Classifier: License :: OSI Approved :: Apache Software License
Classifier: Operating System :: OS Independent
Requires-Dist: boto3
Requires-Dist: psycopg2-binary
